pytransform/__init__.py
pytransform/_pytransform.so
zwlib/__init__.py
zwlib/zwlib.py
zwlib-1.2.0.dist-info/METADATA
zwlib-1.2.0.dist-info/WHEEL
zwlib-1.2.0.dist-info/top_level.txt
zwlib-1.2.0.dist-info/RECORD
